kryptic/__init__.py
kryptic/_import.py
kryptic/generator/__init__.py
kryptic/generator/generator.py
kryptic/generator/generator_test.py
kryptic-1.0.dist-info/LICENSE
kryptic-1.0.dist-info/METADATA
kryptic-1.0.dist-info/WHEEL
kryptic-1.0.dist-info/top_level.txt
kryptic-1.0.dist-info/RECORD
