Metadata-Version: 2.1
Name: kryptic
Version: 1.0
Summary: A tool for generating passwords
Home-page: UNKNOWN
License: MIT
Platform: UNKNOWN
Requires-Python: >=3.6.0
Requires-Dist: secrets
